{"expireTime":9007200869033791000,"key":"transformer-remark-markdown-ast-9de1743ae1318b2a6429bfb849358165-gatsby-remark-imagesgatsby-remark-external-linksgatsby-remark-prismjs-","val":{"type":"root","children":[{"type":"heading","depth":1,"children":[{"type":"text","value":"Descripcion general","position":{"start":{"line":1,"column":3,"offset":2},"end":{"line":1,"column":22,"offset":21},"indent":[]}}],"position":{"start":{"line":1,"column":1,"offset":0},"end":{"line":1,"column":22,"offset":21},"indent":[]}},{"type":"list","ordered":false,"start":null,"spread":false,"children":[{"type":"listItem","spread":false,"checked":null,"children":[{"type":"paragraph","children":[{"type":"text","value":"instalar instalar python en el sistema operativo","position":{"start":{"line":2,"column":3,"offset":24},"end":{"line":2,"column":51,"offset":72},"indent":[]}}],"position":{"start":{"line":2,"column":3,"offset":24},"end":{"line":2,"column":51,"offset":72},"indent":[]}}],"position":{"start":{"line":2,"column":1,"offset":22},"end":{"line":2,"column":51,"offset":72},"indent":[]}},{"type":"listItem","spread":false,"checked":null,"children":[{"type":"paragraph","children":[{"type":"text","value":"configura path , para que se le reconozca en el sistema.","position":{"start":{"line":3,"column":3,"offset":75},"end":{"line":3,"column":59,"offset":131},"indent":[]}}],"position":{"start":{"line":3,"column":3,"offset":75},"end":{"line":3,"column":59,"offset":131},"indent":[]}}],"position":{"start":{"line":3,"column":1,"offset":73},"end":{"line":3,"column":59,"offset":131},"indent":[]}},{"type":"listItem","spread":false,"checked":null,"children":[{"type":"paragraph","children":[{"type":"text","value":"instalar pip o pip3","position":{"start":{"line":4,"column":3,"offset":134},"end":{"line":4,"column":22,"offset":153},"indent":[]}}],"position":{"start":{"line":4,"column":3,"offset":134},"end":{"line":4,"column":22,"offset":153},"indent":[]}}],"position":{"start":{"line":4,"column":1,"offset":132},"end":{"line":4,"column":22,"offset":153},"indent":[]}},{"type":"listItem","spread":false,"checked":null,"children":[{"type":"paragraph","children":[{"type":"text","value":"instalar y crear los virtualenvs en algun directorio ademas de algun proyecto.","position":{"start":{"line":5,"column":3,"offset":156},"end":{"line":5,"column":81,"offset":234},"indent":[]}}],"position":{"start":{"line":5,"column":3,"offset":156},"end":{"line":5,"column":81,"offset":234},"indent":[]}}],"position":{"start":{"line":5,"column":1,"offset":154},"end":{"line":5,"column":81,"offset":234},"indent":[]}}],"position":{"start":{"line":2,"column":1,"offset":22},"end":{"line":5,"column":81,"offset":234},"indent":[1,1,1]}},{"type":"heading","depth":1,"children":[{"type":"text","value":"guia basica","position":{"start":{"line":7,"column":3,"offset":238},"end":{"line":7,"column":14,"offset":249},"indent":[]}}],"position":{"start":{"line":7,"column":1,"offset":236},"end":{"line":7,"column":14,"offset":249},"indent":[]}},{"type":"paragraph","children":[{"type":"text","value":"python -m virtualenv CREATE_API-Django","position":{"start":{"line":9,"column":1,"offset":251},"end":{"line":9,"column":39,"offset":289},"indent":[]}}],"position":{"start":{"line":9,"column":1,"offset":251},"end":{"line":9,"column":39,"offset":289},"indent":[]}},{"type":"paragraph","children":[{"type":"text","value":"requeriminetos en el computador previos :\nPip3 install virtualenv","position":{"start":{"line":11,"column":1,"offset":291},"end":{"line":12,"column":24,"offset":356},"indent":[1]}}],"position":{"start":{"line":11,"column":1,"offset":291},"end":{"line":12,"column":24,"offset":356},"indent":[1]}},{"type":"paragraph","children":[{"type":"text","value":"creando mi carpeta para proyectos. \nmkdir carpeta general\ncd carpeta general - > mkdir EntornosVirtuales\ncd carpeta general - > mkdir Proyectos","position":{"start":{"line":14,"column":1,"offset":358},"end":{"line":17,"column":39,"offset":501},"indent":[1,1,1]}}],"position":{"start":{"line":14,"column":1,"offset":358},"end":{"line":17,"column":39,"offset":501},"indent":[1,1,1]}},{"type":"paragraph","children":[{"type":"text","value":"Cd EntornosVirtuales","position":{"start":{"line":19,"column":1,"offset":503},"end":{"line":19,"column":21,"offset":523},"indent":[]}},{"type":"break","position":{"start":{"line":19,"column":21,"offset":523},"end":{"line":20,"column":1,"offset":526},"indent":[1]}},{"type":"text","value":"----python3 -m vent mientornonuevo","position":{"start":{"line":20,"column":1,"offset":526},"end":{"line":20,"column":35,"offset":560},"indent":[]}},{"type":"break","position":{"start":{"line":20,"column":35,"offset":560},"end":{"line":21,"column":1,"offset":563},"indent":[1]}},{"type":"text","value":"----source myFisrtEnvirment/bin/activate.  //on  ","position":{"start":{"line":21,"column":1,"offset":563},"end":{"line":21,"column":50,"offset":612},"indent":[]}}],"position":{"start":{"line":19,"column":1,"offset":503},"end":{"line":21,"column":50,"offset":612},"indent":[1,1]}},{"type":"paragraph","children":[{"type":"text","value":"Cd Proyectos","position":{"start":{"line":23,"column":1,"offset":614},"end":{"line":23,"column":13,"offset":626},"indent":[]}},{"type":"break","position":{"start":{"line":23,"column":13,"offset":626},"end":{"line":24,"column":1,"offset":629},"indent":[1]}},{"type":"text","value":"----pip3 install Django // queda global?","position":{"start":{"line":24,"column":1,"offset":629},"end":{"line":24,"column":41,"offset":669},"indent":[]}},{"type":"break","position":{"start":{"line":24,"column":41,"offset":669},"end":{"line":25,"column":1,"offset":672},"indent":[1]}},{"type":"text","value":"----Django-admin startproject Miproyecto    ","position":{"start":{"line":25,"column":1,"offset":672},"end":{"line":25,"column":45,"offset":716},"indent":[]}}],"position":{"start":{"line":23,"column":1,"offset":614},"end":{"line":25,"column":45,"offset":716},"indent":[1,1]}},{"type":"paragraph","children":[{"type":"text","value":"cd Miproyecto","position":{"start":{"line":27,"column":1,"offset":718},"end":{"line":27,"column":14,"offset":731},"indent":[]}},{"type":"break","position":{"start":{"line":27,"column":14,"offset":731},"end":{"line":28,"column":1,"offset":734},"indent":[1]}},{"type":"text","value":"----python manage.py runserver  ","position":{"start":{"line":28,"column":1,"offset":734},"end":{"line":28,"column":33,"offset":766},"indent":[]}}],"position":{"start":{"line":27,"column":1,"offset":718},"end":{"line":28,"column":33,"offset":766},"indent":[1]}}],"position":{"start":{"line":1,"column":1,"offset":0},"end":{"line":36,"column":1,"offset":774}}}}